falcon_epdb/__init__.py
falcon_epdb-1.1.2.dist-info/LICENSE
falcon_epdb-1.1.2.dist-info/WHEEL
falcon_epdb-1.1.2.dist-info/METADATA
falcon_epdb-1.1.2.dist-info/RECORD
