Metadata-Version: 2.1
Name: falcon-epdb
Version: 1.1.2
Summary: Interactive debugging for your Falco apps
Home-page: https://github.com/jcwilson/falcon-epdb
License: BSD-3-Clause
Author: Josh Wilson
Author-email: josh.wilson@fivestars.com
Requires-Python: >=2.7, !=3.0.*, !=3.1.*, !=3.2.*, !=3.3.*
Classifier: Development Status :: 3 - Alpha
Classifier: Environment :: Web Environment
Classifier: Intended Audience :: Developers
Classifier: Intended Audience :: Information Technology
Classifier: License :: OSI Approved :: BSD License
Classifier: Natural Language :: English
Classifier: Programming Language :: Python
Classifier: Programming Language :: Python :: 2
Classifier: Programming Language :: Python :: 2.7
Classifier: Programming Language :: Python :: 3
Classifier: Programming Language :: Python :: 3.4
Classifier: Programming Language :: Python :: 3.5
Classifier: Programming Language :: Python :: 3.6
Classifier: Programming Language :: Python :: 3.7
Classifier: Topic :: Internet :: WWW/HTTP :: Dynamic Content :: CGI Tools/Libraries
Classifier: Topic :: Internet :: WWW/HTTP :: WSGI :: Middleware
Provides-Extra: fernet
Provides-Extra: jwt
Requires-Dist: PyJWT (>=1.7,<2.0); extra == "jwt"
Requires-Dist: cryptography (>=2.5,<3.0); extra == "fernet"
Requires-Dist: epdb (>=0.15.1,<0.16.0)
Project-URL: Documentation, https://falcon-epdb.readthedocs.io/
Project-URL: Repository, https://github.com/jcwilson/falcon-epdb
